[{"source": "http://feeds.bbci.co.uk/news/rss.xml", "title": "Allergy emergencies double in recent years in England", "description": "Dangerous allergic reactions led to more than 25,000 hospital stays in the year up to March 2023.", "link": "https://www.bbc.co.uk/news/health-66330268?at_medium=RSS&at_campaign=KARANGA", "date_published": "2023-07-27T23:10:48+00:00", "persistent": false, "dead": false, "artist": null, "album": null, "user": null, "language": "en-US", "thumbnail": null}, {"source": "http://feeds.bbci.co.uk/news/rss.xml", "title": "Donald Trump faces further charges in Mar-a-Lago documents inquiry", "description": "Another Trump employee is also charged in the Mar-a-Lago classified documents case.", "link": "https://www.bbc.co.uk/news/world-us-canada-66333370?at_medium=RSS&at_campaign=KARANGA", "date_published": "2023-07-27T23:09:24+00:00", "persistent": false, "dead": false, "artist": null, "album": null, "user": null, "language": "en-US", "thumbnail": null}, {"source": "http://feeds.bbci.co.uk/news/rss.xml", "title": "Disabled flyers angry at airline 'double charging'", "description": "Many carriers do not follow official guidance on reduced prices for care assistants, the BBC finds.", "link": "https://www.bbc.co.uk/news/disability-66177998?at_medium=RSS&at_campaign=KARANGA", "date_published": "2023-07-27T23:05:15+00:00", "persistent": false, "dead": false, "artist": null, "album": null, "user": null, "language": "en-US", "thumbnail": null}, {"source": "http://feeds.bbci.co.uk/news/rss.xml", "title": "The Papers: 'Global boiling' and 'Harry hacking claim thrown out'", "description": "Many of Friday's front pages lead on the UN's warning that the world is in its \"global boiling\" era.", "link": "https://www.bbc.co.uk/news/blogs-the-papers-66333004?at_medium=RSS&at_campaign=KARANGA", "date_published": "2023-07-27T23:03:27+00:00", "persistent": false, "dead": false, "artist": null, "album": null, "user": null, "language": "en-US", "thumbnail": null}, {"source": "http://feeds.bbci.co.uk/news/rss.xml", "title": "James family 'together and healthy' after son collapse", "description": "LeBron James says his family is \"together, safe and healthy\", after son Bronny, 18, suffers a cardiac arrest.", "link": "https://www.bbc.co.uk/sport/basketball/66332787?at_medium=RSS&at_campaign=KARANGA", "date_published": "2023-07-27T20:12:59+00:00", "persistent": false, "dead": false, "artist": null, "album": null, "user": null, "language": "en-US", "thumbnail": null}, {"source": "http://feeds.bbci.co.uk/news/rss.xml", "title": "Niger coup makes the troubled Sahel region yet more fragile", "description": "One of the few democracies left in the Sahel, Niger now faces military rule just like its neighbours.", "link": "https://www.bbc.co.uk/news/world-africa-66322914?at_medium=RSS&at_campaign=KARANGA", "date_published": "2023-07-27T19:29:32+00:00", "persistent": false, "dead": false, "artist": null, "album": null, "user": null, "language": "en-US", "thumbnail": null}, {"source": "http://feeds.bbci.co.uk/news/rss.xml", "title": "Ashes 2023: Harry Brook could have same impact as Kevin Pietersen - Michael Vaughan", "description": "Harry Brook could have a similar impact for England as Kevin Pietersen, says former captain Michael Vaughan.", "link": "https://www.bbc.co.uk/sport/cricket/66315377?at_medium=RSS&at_campaign=KARANGA", "date_published": "2023-07-27T19:19:57+00:00", "persistent": false, "dead": false, "artist": null, "album": null, "user": null, "language": "en-US", "thumbnail": null}, {"source": "http://feeds.bbci.co.uk/news/rss.xml", "title": "Trump lawyers meet federal prosecutors in election probe", "description": "Speculation mounts that Mr Trump will soon be charged over efforts to overturn his 2020 election loss.", "link": "https://www.bbc.co.uk/news/world-us-canada-66329430?at_medium=RSS&at_campaign=KARANGA", "date_published": "2023-07-27T19:16:31+00:00", "persistent": false, "dead": false, "artist": null, "album": null, "user": null, "language": "en-US", "thumbnail": null}, {"source": "http://feeds.bbci.co.uk/news/rss.xml", "title": "Moises Caicedo: Brighton reject Chelsea's \u00a380m bid for midfielder", "description": "Brighton reject an \u00a380m bid for midfielder Moises Caicedo from Premier League rivals Chelsea.", "link": "https://www.bbc.co.uk/sport/football/66330292?at_medium=RSS&at_campaign=KARANGA", "date_published": "2023-07-27T19:11:01+00:00", "persistent": false, "dead": false, "artist": null, "album": null, "user": null, "language": "en-US", "thumbnail": null}, {"source": "http://feeds.bbci.co.uk/news/rss.xml", "title": "The 'world's hottest month' explained... in 60 seconds", "description": "With July set \"virtually certain\" to be the warmest month on record, BBC Weather has this analysis.", "link": "https://www.bbc.co.uk/news/world-66332670?at_medium=RSS&at_campaign=KARANGA", "date_published": "2023-07-27T18:49:19+00:00", "persistent": false, "dead": false, "artist": null, "album": null, "user": null, "language": "en-US", "thumbnail": null}, {"source": "http://feeds.bbci.co.uk/news/rss.xml", "title": "The Ashes 2023: Australia edge England on first day of fifth Test", "description": "England face a battle to level the Ashes after Australia enjoy the better of the first day of the fifth Test at The Oval.", "link": "https://www.bbc.co.uk/sport/cricket/66329980?at_medium=RSS&at_campaign=KARANGA", "date_published": "2023-07-27T18:23:47+00:00", "persistent": false, "dead": false, "artist": null, "album": null, "user": null, "language": "en-US", "thumbnail": null}, {"source": "http://feeds.bbci.co.uk/news/rss.xml", "title": "Jordan Henderson: Liverpool captain's Saudi Arabia move has 'tarnished his reputation' as LGBTQ+ ally", "description": "Jordan Henderson has joined Saudi Arabian side Al-Ettifaq, but in doing so much of the LGBTQ+ community has been left disappointed in him.", "link": "https://www.bbc.co.uk/sport/football/66324791?at_medium=RSS&at_campaign=KARANGA", "date_published": "2023-07-27T18:23:34+00:00", "persistent": false, "dead": false, "artist": null, "album": null, "user": null, "language": "en-US", "thumbnail": null}, {"source": "http://feeds.bbci.co.uk/news/rss.xml", "title": "The Ashes highlights: England v Australia - fifth Test, day one at The Oval", "description": "England face a battle to level the Ashes after Australia enjoy the better of the first day of the fifth Test at The Oval.", "link": "https://www.bbc.co.uk/sport/av/cricket/66330984?at_medium=RSS&at_campaign=KARANGA", "date_published": "2023-07-27T18:10:27+00:00", "persistent": false, "dead": false, "artist": null, "album": null, "user": null, "language": "en-US", "thumbnail": null}, {"source": "http://feeds.bbci.co.uk/news/rss.xml", "title": "Climate change: July set to be world's warmest month on record", "description": "UN chief says we are in an \"era of global boiling\" as July set to be world's warmest month on record.", "link": "https://www.bbc.co.uk/news/science-environment-66322608?at_medium=RSS&at_campaign=KARANGA", "date_published": "2023-07-27T18:09:36+00:00", "persistent": false, "dead": false, "artist": null, "album": null, "user": null, "language": "en-US", "thumbnail": null}, {"source": "http://feeds.bbci.co.uk/news/rss.xml", "title": "Ukraine war: Kyiv claims success as southern fighting intensifies", "description": "Ukraine's armed forces say they are solidifying positions after an advance east of Zaporizhzhia.", "link": "https://www.bbc.co.uk/news/world-europe-66323354?at_medium=RSS&at_campaign=KARANGA", "date_published": "2023-07-27T17:13:36+00:00", "persistent": false, "dead": false, "artist": null, "album": null, "user": null, "language": "en-US", "thumbnail": null}, {"source": "http://feeds.bbci.co.uk/news/rss.xml", "title": "The Ashes: Chris Woakes strikes to remove David Warner for 24", "description": "England's Chris Woakes strikes to remove David Warner for 24 as Australia lose their first wicket on day one of the fifth Ashes Test at The Oval.", "link": "https://www.bbc.co.uk/sport/av/cricket/66330989?at_medium=RSS&at_campaign=KARANGA", "date_published": "2023-07-27T17:09:53+00:00", "persistent": false, "dead": false, "artist": null, "album": null, "user": null, "language": "en-US", "thumbnail": null}, {"source": "http://feeds.bbci.co.uk/news/rss.xml", "title": "Inter Club D'Escaldes 2-1 Hibernian: Easter Road suffer shock defeat in Andorra", "description": "Hibernian suffer a calamitous defeat at the hands of Andorran side Inter Club d'Escaldes in the first leg of their Europa Conference League second qualifying round tie.", "link": "https://www.bbc.co.uk/sport/football/66330843?at_medium=RSS&at_campaign=KARANGA", "date_published": "2023-07-27T16:57:09+00:00", "persistent": false, "dead": false, "artist": null, "album": null, "user": null, "language": "en-US", "thumbnail": null}, {"source": "http://feeds.bbci.co.uk/news/rss.xml", "title": "England v Denmark: Keira Walsh says England boss Sarina Wiegman wants her to take responsibility", "description": "England midfielder Keira Walsh says she feels more responsibility on the pitch under manager Sarina Wiegman.", "link": "https://www.bbc.co.uk/sport/football/66321244?at_medium=RSS&at_campaign=KARANGA", "date_published": "2023-07-27T16:55:34+00:00", "persistent": false, "dead": false, "artist": null, "album": null, "user": null, "language": "en-US", "thumbnail": null}, {"source": "http://feeds.bbci.co.uk/news/rss.xml", "title": "Man Utd takeover: Fan protest group fears 18-month process", "description": "The 1958 Group, a Manchester United fan protest organisation, tells BBC Sport about its concerns over the continued involvement of the Glazer family.", "link": "https://www.bbc.co.uk/sport/football/66322345?at_medium=RSS&at_campaign=KARANGA", "date_published": "2023-07-27T16:50:15+00:00", "persistent": false, "dead": false, "artist": null, "album": null, "user": null, "language": "en-US", "thumbnail": null}, {"source": "http://feeds.bbci.co.uk/news/rss.xml", "title": "Google alert failed to warn people of Turkey earthquake", "description": "The tech giant claims millions of people were sent a warning before the deadly earthquake earlier this year.", "link": "https://www.bbc.co.uk/news/technology-66316462?at_medium=RSS&at_campaign=KARANGA", "date_published": "2023-07-27T16:01:54+00:00", "persistent": false, "dead": false, "artist": null, "album": null, "user": null, "language": "en-US", "thumbnail": null}, {"source": "http://feeds.bbci.co.uk/news/rss.xml", "title": "Gatwick strikes called off by ground staff", "description": "A planned four-day walkout from Friday is cancelled after revised pay offers are accepted.", "link": "https://www.bbc.co.uk/news/business-66324951?at_medium=RSS&at_campaign=KARANGA", "date_published": "2023-07-27T15:06:55+00:00", "persistent": false, "dead": false, "artist": null, "album": null, "user": null, "language": "en-US", "thumbnail": null}, {"source": "http://feeds.bbci.co.uk/news/rss.xml", "title": "Leicester: Elephant Man statue plan shelved as appeal falls short", "description": "A historian and biographer now says \"no-one is interested\" in her plan to honour John Merrick.", "link": "https://www.bbc.co.uk/news/uk-england-leicestershire-66328693?at_medium=RSS&at_campaign=KARANGA", "date_published": "2023-07-27T15:00:01+00:00", "persistent": false, "dead": false, "artist": null, "album": null, "user": null, "language": "en-US", "thumbnail": null}, {"source": "http://feeds.bbci.co.uk/news/rss.xml", "title": "Andrew Malkinson: Why are some wrongfully convicted prisoners charged jail living costs?", "description": "Money for \"board and lodging\" in jail is sometimes deducted from former prisoners' compensation.", "link": "https://www.bbc.co.uk/news/uk-66324801?at_medium=RSS&at_campaign=KARANGA", "date_published": "2023-07-27T14:05:14+00:00", "persistent": false, "dead": false, "artist": null, "album": null, "user": null, "language": "en-US", "thumbnail": null}, {"source": "http://feeds.bbci.co.uk/news/rss.xml", "title": "The Ashes: England lose Stokes, Bairstow and Brook in quick succession", "description": "England lose captain Ben Stokes, Jonny Bairstow and Harry Brook for just 19 runs on day one of the fifth Ashes Test at the Oval.", "link": "https://www.bbc.co.uk/sport/av/cricket/66328457?at_medium=RSS&at_campaign=KARANGA", "date_published": "2023-07-27T14:00:48+00:00", "persistent": false, "dead": false, "artist": null, "album": null, "user": null, "language": "en-US", "thumbnail": null}, {"source": "http://feeds.bbci.co.uk/news/rss.xml", "title": "World Fencing Championships: Ukraine's Olga Kharlan disqualified for refusing Russian Anna Smirnov's handshake", "description": "Ukrainian fencer Olga Kharlan is disqualified from the World Fencing Championships for refusing to shake hands with Russian Anna Smirnova.", "link": "https://www.bbc.co.uk/sport/fencing/66322668?at_medium=RSS&at_campaign=KARANGA", "date_published": "2023-07-27T13:55:42+00:00", "persistent": false, "dead": false, "artist": null, "album": null, "user": null, "language": "en-US", "thumbnail": null}, {"source": "http://feeds.bbci.co.uk/news/rss.xml", "title": "Coutts Bank boss quits over Farage account row", "description": "Coutts Bank boss quits over handling of Nigel Farage account, which \"fell below bank\u2019s high standards of personal service\"", "link": "https://www.bbc.co.uk/news/business-66328666?at_medium=RSS&at_campaign=KARANGA", "date_published": "2023-07-27T13:22:28+00:00", "persistent": false, "dead": false, "artist": null, "album": null, "user": null, "language": "en-US", "thumbnail": null}, {"source": "http://feeds.bbci.co.uk/news/rss.xml", "title": "Women's World Cup 2023: Nigeria stun co-hosts Australia with comeback win - highlights", "description": "Watch highlights as Nigeria come from a goal down to beat Australia 3-2 in Brisbane and leave the co-hosts facing a battle to qualify for the last 16 of the Women's World Cup.", "link": "https://www.bbc.co.uk/sport/av/football/66269261?at_medium=RSS&at_campaign=KARANGA", "date_published": "2023-07-27T13:20:04+00:00", "persistent": false, "dead": false, "artist": null, "album": null, "user": null, "language": "en-US", "thumbnail": null}, {"source": "http://feeds.bbci.co.uk/news/rss.xml", "title": "The Ashes: Harry Brook hits 50 off 44 balls - watch his best shots", "description": "Watch Harry Brooks' best shots as he reaches 50 not out off 44 balls on day one of the fifth Ashes Test at the Oval.", "link": "https://www.bbc.co.uk/sport/av/cricket/66325969?at_medium=RSS&at_campaign=KARANGA", "date_published": "2023-07-27T13:01:08+00:00", "persistent": false, "dead": false, "artist": null, "album": null, "user": null, "language": "en-US", "thumbnail": null}, {"source": "http://feeds.bbci.co.uk/news/rss.xml", "title": "Iran protests: Return of morality police met by defiance", "description": "The hijab police are back on the streets after nearly a year, but protesters are emboldened.", "link": "https://www.bbc.co.uk/news/world-middle-east-66304495?at_medium=RSS&at_campaign=KARANGA", "date_published": "2023-07-27T12:48:06+00:00", "persistent": false, "dead": false, "artist": null, "album": null, "user": null, "language": "en-US", "thumbnail": null}, {"source": "http://feeds.bbci.co.uk/news/rss.xml", "title": "Woman claims police officer threatened her at Tom Jones gig", "description": "She says the officer flashed his badge to try to avoid being thrown out of the Tom Jones show.", "link": "https://www.bbc.co.uk/news/uk-wales-66313670?at_medium=RSS&at_campaign=KARANGA", "date_published": "2023-07-27T12:46:33+00:00", "persistent": false, "dead": false, "artist": null, "album": null, "user": null, "language": "en-US", "thumbnail": null}, {"source": "http://feeds.bbci.co.uk/news/rss.xml", "title": "Sgt Matiu Ratana shooting: Killer Louis De Zoysa will never be freed", "description": "The Met Police sergeant was shot twice at point-blank range at a custody centre in south London.", "link": "https://www.bbc.co.uk/news/uk-england-london-66314797?at_medium=RSS&at_campaign=KARANGA", "date_published": "2023-07-27T12:30:21+00:00", "persistent": false, "dead": false, "artist": null, "album": null, "user": null, "language": "en-US", "thumbnail": null}, {"source": "http://feeds.bbci.co.uk/news/rss.xml", "title": "Jordan Henderson: Liverpool confirm captain's move to Al-Ettifaq", "description": "Liverpool captain Jordan Henderson joins Saudi Arabian club Al-Ettifaq in a deal worth \u00a312m plus add-ons.", "link": "https://www.bbc.co.uk/sport/football/66185472?at_medium=RSS&at_campaign=KARANGA", "date_published": "2023-07-27T12:14:38+00:00", "persistent": false, "dead": false, "artist": null, "album": null, "user": null, "language": "en-US", "thumbnail": null}, {"source": "http://feeds.bbci.co.uk/news/rss.xml", "title": "Australia 2-3 Nigeria: Matildas face battle to reach last 16 at Fifa Women's World Cup", "description": "Nigeria come from behind to beat Australia and leave the co-hosts facing a battle to qualify for the last 16 of the Fifa Women's World Cup.", "link": "https://www.bbc.co.uk/sport/football/66290741?at_medium=RSS&at_campaign=KARANGA", "date_published": "2023-07-27T12:08:50+00:00", "persistent": false, "dead": false, "artist": null, "album": null, "user": null, "language": "en-US", "thumbnail": null}, {"source": "http://feeds.bbci.co.uk/news/rss.xml", "title": "Sin\u00e9ad O'Connor's life in pictures", "description": "Striking shots from the life and career of the late singer and activist.", "link": "https://www.bbc.co.uk/news/in-pictures-66323955?at_medium=RSS&at_campaign=KARANGA", "date_published": "2023-07-27T12:04:58+00:00", "persistent": false, "dead": false, "artist": null, "album": null, "user": null, "language": "en-US", "thumbnail": null}, {"source": "http://feeds.bbci.co.uk/news/rss.xml", "title": "Humza Yousaf reveals Scots citizenship and passport plan", "description": "The Scottish government has published the latest prospectus in its series of independence papers.", "link": "https://www.bbc.co.uk/news/uk-scotland-66312190?at_medium=RSS&at_campaign=KARANGA", "date_published": "2023-07-27T12:02:44+00:00", "persistent": false, "dead": false, "artist": null, "album": null, "user": null, "language": "en-US", "thumbnail": null}, {"source": "http://feeds.bbci.co.uk/news/rss.xml", "title": "'Routine' housing of child asylum seekers in hotels unlawful, High Court rules", "description": "Hundreds of children have gone missing from hotels, with concerns some have been groomed by gangs.", "link": "https://www.bbc.co.uk/news/uk-politics-66325644?at_medium=RSS&at_campaign=KARANGA", "date_published": "2023-07-27T11:34:52+00:00", "persistent": false, "dead": false, "artist": null, "album": null, "user": null, "language": "en-US", "thumbnail": null}, {"source": "http://feeds.bbci.co.uk/news/rss.xml", "title": "Niger coup: Captive President Bazoum defiant after takeover", "description": "Mohamed Bazoum takes to Twitter as the army chief comes out in support of the takeover.", "link": "https://www.bbc.co.uk/news/world-africa-66324875?at_medium=RSS&at_campaign=KARANGA", "date_published": "2023-07-27T11:23:40+00:00", "persistent": false, "dead": false, "artist": null, "album": null, "user": null, "language": "en-US", "thumbnail": null}, {"source": "http://feeds.bbci.co.uk/news/rss.xml", "title": "Rhodes fires: View from Glystra beach", "description": "The BBC's Azadeh Moshiri has been to Glystra beach near Kiotari, one of the areas worst affected by wildfires.", "link": "https://www.bbc.co.uk/news/world-europe-66326435?at_medium=RSS&at_campaign=KARANGA", "date_published": "2023-07-27T11:21:11+00:00", "persistent": false, "dead": false, "artist": null, "album": null, "user": null, "language": "en-US", "thumbnail": null}, {"source": "http://feeds.bbci.co.uk/news/rss.xml", "title": "The Ashes: England lose Ben Duckett, Zak Crawley & Joe Root for 11 runs", "description": "England lose Ben Duckett, Zak Crawley and Joe Root to go from 62-0 to 73-3 in the space of three-and-a-half overs on day one of the fifth Ashes Test.", "link": "https://www.bbc.co.uk/sport/av/cricket/66325965?at_medium=RSS&at_campaign=KARANGA", "date_published": "2023-07-27T11:19:01+00:00", "persistent": false, "dead": false, "artist": null, "album": null, "user": null, "language": "en-US", "thumbnail": null}, {"source": "http://feeds.bbci.co.uk/news/rss.xml", "title": "Croydon tram crash: Operators fined \u00a314m after seven people killed", "description": "Transport for London is among operators fined after seven people died in the Croydon tram crash.", "link": "https://www.bbc.co.uk/news/uk-england-london-66323171?at_medium=RSS&at_campaign=KARANGA", "date_published": "2023-07-27T11:15:22+00:00", "persistent": false, "dead": false, "artist": null, "album": null, "user": null, "language": "en-US", "thumbnail": null}, {"source": "http://feeds.bbci.co.uk/news/rss.xml", "title": "Sin\u00e9ad O'Connor's death not treated as suspicious, police say", "description": "The Irish singer was found dead at her London home on Wednesday shortly after 11:00 BST, aged 56.", "link": "https://www.bbc.co.uk/news/entertainment-arts-66325176?at_medium=RSS&at_campaign=KARANGA", "date_published": "2023-07-27T11:12:08+00:00", "persistent": false, "dead": false, "artist": null, "album": null, "user": null, "language": "en-US", "thumbnail": null}, {"source": "http://feeds.bbci.co.uk/news/rss.xml", "title": "Last orders for takeaway pub pints as Covid rules expire", "description": "Relaxed licensing rules brought in during Covid in England and Wakes will soon come to an end.", "link": "https://www.bbc.co.uk/news/uk-politics-66318476?at_medium=RSS&at_campaign=KARANGA", "date_published": "2023-07-27T10:55:26+00:00", "persistent": false, "dead": false, "artist": null, "album": null, "user": null, "language": "en-US", "thumbnail": null}, {"source": "http://feeds.bbci.co.uk/news/rss.xml", "title": "Wildcat kittens bring hope for endangered species", "description": "Eleven kittens born in captivity could help bring wildcats back from 'brink of extinction' in Scotland.", "link": "https://www.bbc.co.uk/news/uk-scotland-highlands-islands-66322190?at_medium=RSS&at_campaign=KARANGA", "date_published": "2023-07-27T10:44:43+00:00", "persistent": false, "dead": false, "artist": null, "album": null, "user": null, "language": "en-US", "thumbnail": null}, {"source": "http://feeds.bbci.co.uk/news/rss.xml", "title": "Mercury Prize 2023: Arctic Monkeys, Jessie Ware and Fred Again lead shortlist", "description": "The Monkeys are nominated for a record fifth time, in a shortlist that otherwise focuses on London.", "link": "https://www.bbc.co.uk/news/entertainment-arts-66312276?at_medium=RSS&at_campaign=KARANGA", "date_published": "2023-07-27T10:05:09+00:00", "persistent": false, "dead": false, "artist": null, "album": null, "user": null, "language": "en-US", "thumbnail": null}, {"source": "http://feeds.bbci.co.uk/news/rss.xml", "title": "English National Opera's deadline to move from London extended", "description": "The English National Opera is given a deadline extension of several years to move out of London.", "link": "https://www.bbc.co.uk/news/uk-england-london-66315964?at_medium=RSS&at_campaign=KARANGA", "date_published": "2023-07-27T10:02:47+00:00", "persistent": false, "dead": false, "artist": null, "album": null, "user": null, "language": "en-US", "thumbnail": null}, {"source": "http://feeds.bbci.co.uk/news/rss.xml", "title": "Prince Harry set for court showdown with Sun publisher", "description": "A judge rules that a High Court trial over the Duke of Sussex's privacy breach claims can go ahead.", "link": "https://www.bbc.co.uk/news/uk-66322279?at_medium=RSS&at_campaign=KARANGA", "date_published": "2023-07-27T10:01:26+00:00", "persistent": false, "dead": false, "artist": null, "album": null, "user": null, "language": "en-US", "thumbnail": null}, {"source": "http://feeds.bbci.co.uk/news/rss.xml", "title": "Portugal 2-0 Vietnam: World Cup debutants set up USA showdown with victory", "description": "Portugal earn a face off with reigning champions United States for a place in the last 16 of the Women's World Cup with an impressive win over Vietnam.", "link": "https://www.bbc.co.uk/sport/football/66290732?at_medium=RSS&at_campaign=KARANGA", "date_published": "2023-07-27T09:44:57+00:00", "persistent": false, "dead": false, "artist": null, "album": null, "user": null, "language": "en-US", "thumbnail": null}, {"source": "http://feeds.bbci.co.uk/news/rss.xml", "title": "Man wrongly jailed for 17 years says 'world finally knows truth'", "description": "The miscarriage-of-justice victim talks about his first night since his conviction was overturned.", "link": "https://www.bbc.co.uk/news/uk-england-manchester-66323436?at_medium=RSS&at_campaign=KARANGA", "date_published": "2023-07-27T09:43:02+00:00", "persistent": false, "dead": false, "artist": null, "album": null, "user": null, "language": "en-US", "thumbnail": null}, {"source": "http://feeds.bbci.co.uk/news/rss.xml", "title": "Travis Scott insists Utopia gig at Egypt's pyramids will happen", "description": "The rapper's spectacular show at the Egyptian landmark is officially cancelled at the last minute.", "link": "https://www.bbc.co.uk/news/newsbeat-66323295?at_medium=RSS&at_campaign=KARANGA", "date_published": "2023-07-27T08:49:29+00:00", "persistent": false, "dead": false, "artist": null, "album": null, "user": null, "language": "en-US", "thumbnail": null}, {"source": "http://feeds.bbci.co.uk/news/rss.xml", "title": "Myanmar Aung San Suu Kyi moved out of jail to house arrest", "description": "Myanmar's civilian leader is serving a 33-year jail sentence after being ousted in a military coup.", "link": "https://www.bbc.co.uk/news/world-asia-66323190?at_medium=RSS&at_campaign=KARANGA", "date_published": "2023-07-27T08:48:41+00:00", "persistent": false, "dead": false, "artist": null, "album": null, "user": null, "language": "en-US", "thumbnail": null}, {"source": "http://feeds.bbci.co.uk/news/rss.xml", "title": "Co-op warns rising crime could create 'no-go' areas for shops", "description": "The retailer says crime levels in its stores have shot up by more than one third over the past year.", "link": "https://www.bbc.co.uk/news/business-66323140?at_medium=RSS&at_campaign=KARANGA", "date_published": "2023-07-27T08:46:35+00:00", "persistent": false, "dead": false, "artist": null, "album": null, "user": null, "language": "en-US", "thumbnail": null}, {"source": "http://feeds.bbci.co.uk/news/rss.xml", "title": "Women's World Cup: Lucy Bronze happy to take 1-0 as Lionesses seek last 16", "description": "England defender Lucy Bronze says it would not matter if they won the Women's World Cup with 1-0 scorelines in every game.", "link": "https://www.bbc.co.uk/sport/football/66290755?at_medium=RSS&at_campaign=KARANGA", "date_published": "2023-07-27T08:43:06+00:00", "persistent": false, "dead": false, "artist": null, "album": null, "user": null, "language": "en-US", "thumbnail": null}, {"source": "http://feeds.bbci.co.uk/news/rss.xml", "title": "Women's World Cup: England captain Millie Bright on her football motivations", "description": "Millie Bright opens up about her experiences with childhood illness, being made England captain and what drives the Lionesses, ahead of Friday's game against Denmark.", "link": "https://www.bbc.co.uk/sport/av/football/66323428?at_medium=RSS&at_campaign=KARANGA", "date_published": "2023-07-27T08:10:28+00:00", "persistent": false, "dead": false, "artist": null, "album": null, "user": null, "language": "en-US", "thumbnail": null}, {"source": "http://feeds.bbci.co.uk/news/rss.xml", "title": "Wizz Air passengers may get refunds as claims reopened", "description": "The aviation regulator is concerned passengers have not been compensated properly for disrupted flights.", "link": "https://www.bbc.co.uk/news/business-66322764?at_medium=RSS&at_campaign=KARANGA", "date_published": "2023-07-27T07:45:31+00:00", "persistent": false, "dead": false, "artist": null, "album": null, "user": null, "language": "en-US", "thumbnail": null}, {"source": "http://feeds.bbci.co.uk/news/rss.xml", "title": "Women's World Cup 2023: Lindsey Horan header earns USA draw against Netherlands - highlights", "description": "Watch highlights as Lindsey Horan's second-half header denies the Netherlands a famous win over defending champions the United States Women's World Cup in Wellington.", "link": "https://www.bbc.co.uk/sport/av/football/66268683?at_medium=RSS&at_campaign=KARANGA", "date_published": "2023-07-27T06:37:04+00:00", "persistent": false, "dead": false, "artist": null, "album": null, "user": null, "language": "en-US", "thumbnail": null}, {"source": "http://feeds.bbci.co.uk/news/rss.xml", "title": "Shell profits drop as oil and gas prices fall", "description": "The oil and gas giant makes profits of $5bn after energy prices fall.", "link": "https://www.bbc.co.uk/news/business-66315117?at_medium=RSS&at_campaign=KARANGA", "date_published": "2023-07-27T06:30:39+00:00", "persistent": false, "dead": false, "artist": null, "album": null, "user": null, "language": "en-US", "thumbnail": null}, {"source": "http://feeds.bbci.co.uk/news/rss.xml", "title": "Chelsea 1-1 Newcastle: Mauricio Pochettino says 'tough' squad decisions must be made", "description": "Chelsea boss Mauricio Pochettino says he must make tough decisions as he aims to reduce his \"massive squad\" before the start of the new season.", "link": "https://www.bbc.co.uk/sport/football/66316074?at_medium=RSS&at_campaign=KARANGA", "date_published": "2023-07-27T06:17:09+00:00", "persistent": false, "dead": false, "artist": null, "album": null, "user": null, "language": "en-US", "thumbnail": null}, {"source": "http://feeds.bbci.co.uk/news/rss.xml", "title": "Real Madrid 2-0 Manchester United: Jude Bellingham scores in man-of-the-match performance", "description": "Jude Bellingham scores in a man-of-the-match performance as Real Madrid beat Manchester United in a pre-season friendly in Houston.", "link": "https://www.bbc.co.uk/sport/football/66321914?at_medium=RSS&at_campaign=KARANGA", "date_published": "2023-07-27T05:47:14+00:00", "persistent": false, "dead": false, "artist": null, "album": null, "user": null, "language": "en-US", "thumbnail": null}, {"source": "http://feeds.bbci.co.uk/news/rss.xml", "title": "Barbie: Dancer's three months as a Ken doll in smash-hit film", "description": "Gustave Die had to shave his body hair daily and be covered in paint for the hit movie.", "link": "https://www.bbc.co.uk/news/uk-england-tyne-66313739?at_medium=RSS&at_campaign=KARANGA", "date_published": "2023-07-27T05:38:45+00:00", "persistent": false, "dead": false, "artist": null, "album": null, "user": null, "language": "en-US", "thumbnail": null}, {"source": "http://feeds.bbci.co.uk/news/rss.xml", "title": "Netball World Cup 2023: South Africa ready to 'showcase' historic tournament", "description": "As South Africa prepares to become the first African nation to host the Netball World Cup, shooter Lenize Potgieter tells BBC Sport what to expect.", "link": "https://www.bbc.co.uk/sport/netball/66289279?at_medium=RSS&at_campaign=KARANGA", "date_published": "2023-07-27T05:35:46+00:00", "persistent": false, "dead": false, "artist": null, "album": null, "user": null, "language": "en-US", "thumbnail": null}, {"source": "http://feeds.bbci.co.uk/news/rss.xml", "title": "North Korea: Kim Jong Un shows off missiles to Russia defence chief Shoigu", "description": "The tour comes amid accusations that Pyongyang is supplying Russia with arms for the Ukraine war.", "link": "https://www.bbc.co.uk/news/world-asia-66321742?at_medium=RSS&at_campaign=KARANGA", "date_published": "2023-07-27T05:32:46+00:00", "persistent": false, "dead": false, "artist": null, "album": null, "user": null, "language": "en-US", "thumbnail": null}, {"source": "http://feeds.bbci.co.uk/news/rss.xml", "title": "Isles of Scilly Iron Age warrior was probably a woman", "description": "The findings \"provide evidence of a leading role for a woman in warfare on Iron Age Scilly\".", "link": "https://www.bbc.co.uk/news/uk-england-cornwall-66314179?at_medium=RSS&at_campaign=KARANGA", "date_published": "2023-07-27T05:11:45+00:00", "persistent": false, "dead": false, "artist": null, "album": null, "user": null, "language": "en-US", "thumbnail": null}, {"source": "http://feeds.bbci.co.uk/news/rss.xml", "title": "Singapore to execute first woman on drugs charge for the first time in 20 years", "description": "Sir Richard Branson and activists have called on authorities to spare Saridewi Djamani.", "link": "https://www.bbc.co.uk/news/world-asia-66309347?at_medium=RSS&at_campaign=KARANGA", "date_published": "2023-07-27T05:07:42+00:00", "persistent": false, "dead": false, "artist": null, "album": null, "user": null, "language": "en-US", "thumbnail": null}, {"source": "http://feeds.bbci.co.uk/news/rss.xml", "title": "GAA All-Ireland football final: Dion Dublin learns about Gaelic football", "description": "Dion Dublin joins BBC Sport\u2019s Thomas Niblock on a road trip to learn about Gaelic football and experience the All-Ireland Senior Football Championship.", "link": "https://www.bbc.co.uk/sport/av/gaelic-games/66317273?at_medium=RSS&at_campaign=KARANGA", "date_published": "2023-07-27T05:00:34+00:00", "persistent": false, "dead": false, "artist": null, "album": null, "user": null, "language": "en-US", "thumbnail": null}, {"source": "http://feeds.bbci.co.uk/news/rss.xml", "title": "Fifa Women's World Cup 2023: Jill Roord fires Netherlands ahead against USA", "description": "Jill Roord gives the Netherlands the lead against the USA with a clinical finish from the edge of the box at the Fifa Women's World Cup.", "link": "https://www.bbc.co.uk/sport/av/football/66321868?at_medium=RSS&at_campaign=KARANGA", "date_published": "2023-07-27T04:41:56+00:00", "persistent": false, "dead": false, "artist": null, "album": null, "user": null, "language": "en-US", "thumbnail": null}, {"source": "http://feeds.bbci.co.uk/news/rss.xml", "title": "Sin\u00e9ad O'Connor: Tributes flow for Irish singer dead at 56", "description": "The Irish singer and activist's family have announced the news of her death \"with great sadness\".", "link": "https://www.bbc.co.uk/news/entertainment-arts-66321090?at_medium=RSS&at_campaign=KARANGA", "date_published": "2023-07-27T04:22:20+00:00", "persistent": false, "dead": false, "artist": null, "album": null, "user": null, "language": "en-US", "thumbnail": null}, {"source": "http://feeds.bbci.co.uk/news/rss.xml", "title": "Barbie: Toy maker Mattel looks to more movies as sales fall", "description": "The comments come as Mattel reported a 12% fall in sales for the three months to the end of June.", "link": "https://www.bbc.co.uk/news/business-66321176?at_medium=RSS&at_campaign=KARANGA", "date_published": "2023-07-27T04:21:34+00:00", "persistent": false, "dead": false, "artist": null, "album": null, "user": null, "language": "en-US", "thumbnail": null}, {"source": "http://feeds.bbci.co.uk/news/rss.xml", "title": "Ukraine war: How the offensive in the south has stuttered", "description": "Russians use layers of mines to prevent Ukraine's advance on the southern front.", "link": "https://www.bbc.co.uk/news/world-europe-66306150?at_medium=RSS&at_campaign=KARANGA", "date_published": "2023-07-27T04:15:33+00:00", "persistent": false, "dead": false, "artist": null, "album": null, "user": null, "language": "en-US", "thumbnail": null}, {"source": "http://feeds.bbci.co.uk/news/rss.xml", "title": "USA 1-1 Netherlands: Lindsey Horan rescues the United States from defeat at Women's World Cup", "description": "Captain Lindsey Horan comes to the rescue of defending champions the United States after the Netherlands threaten an upset at the Women's World Cup.", "link": "https://www.bbc.co.uk/sport/football/66290725?at_medium=RSS&at_campaign=KARANGA", "date_published": "2023-07-27T03:20:54+00:00", "persistent": false, "dead": false, "artist": null, "album": null, "user": null, "language": "en-US", "thumbnail": null}, {"source": "http://feeds.bbci.co.uk/news/rss.xml", "title": "Russia-Africa summit: Putin seeks to extend influence", "description": "Russia's president is hosting a summit of African leaders in a bid to increase Moscow's influence.", "link": "https://www.bbc.co.uk/news/world-africa-66300962?at_medium=RSS&at_campaign=KARANGA", "date_published": "2023-07-27T02:34:14+00:00", "persistent": false, "dead": false, "artist": null, "album": null, "user": null, "language": "en-US", "thumbnail": null}, {"source": "http://feeds.bbci.co.uk/news/rss.xml", "title": "Leicester City: Relegated EPL team delight fans on Asia tour", "description": "Under Thai ownership the club won the Premier League before dropping out of English football's top tier.", "link": "https://www.bbc.co.uk/news/business-66241181?at_medium=RSS&at_campaign=KARANGA", "date_published": "2023-07-27T02:13:19+00:00", "persistent": false, "dead": false, "artist": null, "album": null, "user": null, "language": "en-US", "thumbnail": null}, {"source": "http://feeds.bbci.co.uk/news/rss.xml", "title": "Less food for families on summer-holiday support", "description": "Rising prices drive down the value of summer-holiday help for pupils on free school meals.", "link": "https://www.bbc.co.uk/news/education-66243707?at_medium=RSS&at_campaign=KARANGA", "date_published": "2023-07-27T01:40:34+00:00", "persistent": false, "dead": false, "artist": null, "album": null, "user": null, "language": "en-US", "thumbnail": null}, {"source": "http://feeds.bbci.co.uk/news/rss.xml", "title": "Extra hospital beds made available for winter - NHS England", "description": "There will be 5,000 more beds and better planning, but fears remain about staffing and funding.", "link": "https://www.bbc.co.uk/news/health-66319056?at_medium=RSS&at_campaign=KARANGA", "date_published": "2023-07-27T01:38:57+00:00", "persistent": false, "dead": false, "artist": null, "album": null, "user": null, "language": "en-US", "thumbnail": null}, {"source": "http://feeds.bbci.co.uk/news/rss.xml", "title": "Solicitors regulator launches investigation of asylum claim law firms", "description": "Justice Secretary Alex Chalk urges the regulator to use the \"full force of sanctions\" at its disposal.", "link": "https://www.bbc.co.uk/news/uk-politics-66320938?at_medium=RSS&at_campaign=KARANGA", "date_published": "2023-07-27T01:34:00+00:00", "persistent": false, "dead": false, "artist": null, "album": null, "user": null, "language": "en-US", "thumbnail": null}, {"source": "http://feeds.bbci.co.uk/news/rss.xml", "title": "Why Hunter Biden is important to Republicans... in 90 seconds", "description": "The BBC's Anthony Zurcher explains why the US president's son is a presence on the campaign trail.", "link": "https://www.bbc.co.uk/news/world-us-canada-66321186?at_medium=RSS&at_campaign=KARANGA", "date_published": "2023-07-27T01:04:15+00:00", "persistent": false, "dead": false, "artist": null, "album": null, "user": null, "language": "en-US", "thumbnail": null}, {"source": "http://feeds.bbci.co.uk/news/rss.xml", "title": "Swan upping: Royal cygnet numbers drop by 40% in a year", "description": "The historic royal tradition of \"swan upping\" reveals a sharp decline in swan young on the River Thames.", "link": "https://www.bbc.co.uk/news/uk-66317374?at_medium=RSS&at_campaign=KARANGA", "date_published": "2023-07-27T00:55:24+00:00", "persistent": false, "dead": false, "artist": null, "album": null, "user": null, "language": "en-US", "thumbnail": null}, {"source": "http://feeds.bbci.co.uk/news/rss.xml", "title": "Watch: Soldiers announce coup on Niger national TV", "description": "Army spokesperson Col Maj Amadou Abdramane said defence forces had dissolved the constitution, suspended all institutions and closed the West African country\u2019s borders.", "link": "https://www.bbc.co.uk/news/world-africa-66321256?at_medium=RSS&at_campaign=KARANGA", "date_published": "2023-07-27T00:52:35+00:00", "persistent": false, "dead": false, "artist": null, "album": null, "user": null, "language": "en-US", "thumbnail": null}, {"source": "http://feeds.bbci.co.uk/news/rss.xml", "title": "How O'Connor recorded Nothing Compares 2 U", "description": "The star took an obscure Prince song and made it her own, much to his apparent displeasure.", "link": "https://www.bbc.co.uk/news/entertainment-arts-66320163?at_medium=RSS&at_campaign=KARANGA", "date_published": "2023-07-27T00:39:00+00:00", "persistent": false, "dead": false, "artist": null, "album": null, "user": null, "language": "en-US", "thumbnail": null}, {"source": "http://feeds.bbci.co.uk/news/rss.xml", "title": "Herpes deaths: Why did our daughters die after Caesareans?", "description": "Two mothers were bereaved in extraordinary circumstances - and vowed to keep fighting for the truth.", "link": "https://www.bbc.co.uk/news/uk-66168392?at_medium=RSS&at_campaign=KARANGA", "date_published": "2023-07-27T00:34:45+00:00", "persistent": false, "dead": false, "artist": null, "album": null, "user": null, "language": "en-US", "thumbnail": null}]