[{"source": "https://www.youtube.com/feeds/videos.xml?channel_id=UCJKt_QVDyUbqdm3ag_py2eQ", "title": "FastTracker music: Martyn - Synthetic Bitch (GUS PnP clone)", "description": "\"Synthetic Bitch\" by Martyn/Destiny (Mattias Sundling), 2nd at Blacktron Music Compo 1998 (Goa/Psy category).\n\nOpen Cubic Player 2.6.0pre6 and Gravis Ultrasound PnP clone hardware mixing (InterWave).", "link": "https://www.youtube.com/watch?v=3RFXUJv9Uok", "date_published": "2023-09-11T14:50:05+00:00", "bookmarked": false, "dead": null, "artist": "Kuokka77", "album": "Kuokka77", "user": null, "language": "en-US", "thumbnail": "https://i4.ytimg.com/vi/3RFXUJv9Uok/hqdefault.jpg"}]