[{"source": "http://rss.cnn.com/rss/edition.rss", "title": "Haberman reveals why Trump attacked judge and his family in speech", "description": "CNN political contributor Maggie Haberman explains the reasoning behind Donald Trump's attacks on the judge and his family during a speech at his Mar-a-Lago resort after he was arraigned on felony charges.", "link": "https://www.cnn.com/videos/politics/2023/04/05/maggie-haberman-donald-trump-speech-indictment-reaction-sot-cnntm-vpx.cnn", "date_published": "2023-04-05 13:30:09+00:00", "persistent": false, "user": null, "language": "en-US"}]