[{"source": "https://www.youtube.com/feeds/videos.xml?channel_id=UCl2mFZoRqjw_ELax4Yisf6w", "title": "Ad free YouTube client DELISTED from Google search results!", "description": "https://newpipe.net/blog/pinned/announcement/newpipe-net-dmca-google-search/", "link": "https://www.youtube.com/watch?v=JgNArdQhoH4", "date_published": "2023-07-12T16:57:00+00:00", "persistent": false, "dead": false, "artist": null, "album": null, "user": null, "language": "en-US", "thumbnail": "https://i3.ytimg.com/vi/JgNArdQhoH4/hqdefault.jpg"}]