[{"source": "https://www.youtube.com/feeds/videos.xml?channel_id=UCSJPFQdZwrOutnmSFYtbstA", "title": "Drinker does Gaming - Dead Space (Part 4)", "description": "", "link": "https://www.youtube.com/watch?v=uolOkYg1fFc", "date_published": "2023-02-21 22:08:50+00:00", "persistent": false, "user": null, "language": "en-US"}, {"source": "https://www.youtube.com/feeds/videos.xml?channel_id=UCSJPFQdZwrOutnmSFYtbstA", "title": "Ant Man 3 Will Make You Hate Movies", "description": "Ant Man and the Wasp: Quantumania, the first film in Phase 5 of the MCU, is out. And its terrible! Join me as I delve deep into this quantum-level disaster. \n\nWant to help support this channel? \nCheck out my books on Amazon: https://www.amazon.com/Will-Jordan/e/B00BCO7SA8/ref=dp_byline_cont_pop_ebooks_1\nSubscribe on Patreon: https://www.patreon.com/TheCriticalDrinker\nSubscribe on Subscribestar: https://www.subscribestar.com/the-critical-drinker", "link": "https://www.youtube.com/watch?v=va_Oz_MCGR8", "date_published": "2023-02-21 16:51:19+00:00", "persistent": false, "user": null, "language": "en-US"}]