[{"source": "https://www.instalki.pl/aktualnosci", "title": "Windows 11 pozwoli zaoszcz\u0119dzi\u0107 pr\u0105d. Wszystko dzi\u0119ki nowej funkcji - Instalki.pl", "description": "Windows 11 pozwoli zaoszcz\u0119dzi\u0107 pr\u0105d. Wszystko dzi\u0119ki nowej funkcji - Instalki.pl", "link": "https://www.instalki.pl/aktualnosci/software/59990-windows-11-funkcja-pozwalajaca-zaoszczedzic-prad.html", "date_published": "2023-07-21T19:58:23.036592+00:00", "persistent": false, "dead": false, "artist": null, "album": null, "user": null, "language": "pl-PL", "thumbnail": null}, {"source": "https://www.instalki.pl/aktualnosci", "title": "Najpojemniejszy dysk SSD PCIe na \u015bwiecie - Solidigm D5-P5336 szokuje pojemno\u015bci\u0105 - Instalki.pl", "description": "Najpojemniejszy dysk SSD PCIe na \u015bwiecie - Solidigm D5-P5336 szokuje pojemno\u015bci\u0105 - Instalki.pl", "link": "https://www.instalki.pl/aktualnosci/hardware/59989-najpojemniejszy-dysk-ssd-pcie-na-swieciesolidigm-d5-p5336.html", "date_published": "2023-07-21T18:53:26.275731+00:00", "persistent": false, "dead": false, "artist": null, "album": null, "user": null, "language": "pl-PL", "thumbnail": null}, {"source": "https://www.instalki.pl/aktualnosci", "title": "Paliwo taniej a\u017c o 45 groszy na litrze. Potrzebujesz tej nowej aplikacji - Instalki.pl", "description": "Paliwo taniej a\u017c o 45 groszy na litrze. Potrzebujesz tej nowej aplikacji - Instalki.pl", "link": "https://www.instalki.pl/aktualnosci/software/59983-najlepsza-promocja-na-paliwo-najtaniej-ktora-stacja-mol-polska-aplikacja.html", "date_published": "2023-07-21T18:53:26.022722+00:00", "persistent": false, "dead": false, "artist": null, "album": null, "user": null, "language": "pl-PL", "thumbnail": null}, {"source": "https://www.instalki.pl/aktualnosci", "title": "OPPO Reno10 Pro 5G - pierwsze wra\u017cenia. Super\u015bredniak mocny fotograficznie - Instalki.pl", "description": "OPPO Reno10 Pro 5G - pierwsze wra\u017cenia. Super\u015bredniak mocny fotograficznie - Instalki.pl", "link": "https://www.instalki.pl/aktualnosci/hardware/59987-oppo-reno10-pro-5g-pierwsze-wrazenia-opinia.html", "date_published": "2023-07-21T15:28:11.052470+00:00", "persistent": false, "dead": false, "artist": null, "album": null, "user": null, "language": "pl-PL", "thumbnail": null}, {"source": "https://www.instalki.pl/aktualnosci", "title": "Viaplay jednak u nas zostanie? CANAL+ postanowi\u0142o wej\u015b\u0107 do gry - Instalki.pl", "description": "Viaplay jednak u nas zostanie? CANAL+ postanowi\u0142o wej\u015b\u0107 do gry - Instalki.pl", "link": "https://www.instalki.pl/aktualnosci/rozrywka/59988-viaplay-canal-plus-wykupienie-akcji.html", "date_published": "2023-07-21T15:28:10.851114+00:00", "persistent": false, "dead": false, "artist": null, "album": null, "user": null, "language": "pl-PL", "thumbnail": null}, {"source": "https://www.instalki.pl/aktualnosci", "title": "Lekarka streamowa\u0142a operacj\u0119 na TikToku. Straci\u0142a prawo do wykonywania zawodu - Instalki.pl", "description": "Lekarka streamowa\u0142a operacj\u0119 na TikToku. Straci\u0142a prawo do wykonywania zawodu - Instalki.pl", "link": "https://www.instalki.pl/aktualnosci/internet/59984-lekarka-z-tiktoka-stracila-prawo-do-wykonywania-zawodu.html", "date_published": "2023-07-21T14:23:04.992957+00:00", "persistent": false, "dead": false, "artist": null, "album": null, "user": null, "language": "pl-PL", "thumbnail": null}, {"source": "https://www.instalki.pl/aktualnosci", "title": "Szykuje si\u0119 powr\u00f3t Tytusa, Romka i A\u2019Tomka. Nadchodzi nowy film i serial - Instalki.pl", "description": "Szykuje si\u0119 powr\u00f3t Tytusa, Romka i A\u2019Tomka. Nadchodzi nowy film i serial - Instalki.pl", "link": "https://www.instalki.pl/aktualnosci/rozrywka/59982-tytus-romek-i-atomek-serial-film.html", "date_published": "2023-07-21T13:18:12.352564+00:00", "persistent": false, "dead": false, "artist": null, "album": null, "user": null, "language": "pl-PL", "thumbnail": null}, {"source": "https://www.instalki.pl/aktualnosci", "title": "Samochody elektryczne z zakazem wjazdu do kolejnej galerii handlowej w Polsce - Instalki.pl", "description": "Samochody elektryczne z zakazem wjazdu do kolejnej galerii handlowej w Polsce - Instalki.pl", "link": "https://www.instalki.pl/aktualnosci/technika/59981-madison-park-gdansk-zakaz-wjazdu-aut-elektrycznych.html", "date_published": "2023-07-21T12:13:07.000918+00:00", "persistent": false, "dead": false, "artist": null, "album": null, "user": null, "language": "pl-PL", "thumbnail": null}, {"source": "https://www.instalki.pl/aktualnosci", "title": "Dziwny obiekt mruga w stron\u0119 Ziemi co 30 minut od 1988 roku - Instalki.pl", "description": "Dziwny obiekt mruga w stron\u0119 Ziemi co 30 minut od 1988 roku - Instalki.pl", "link": "https://www.instalki.pl/aktualnosci/nauka/59980-gpm-j1839-10-mruga-w-strone-ziemi.html", "date_published": "2023-07-21T11:07:56.902719+00:00", "persistent": false, "dead": false, "artist": null, "album": null, "user": null, "language": "pl-PL", "thumbnail": null}, {"source": "https://www.instalki.pl/aktualnosci", "title": "Cyfrowa nie\u015bmiertelno\u015b\u0107 ju\u017c dost\u0119pna. Wirtualny awatar za tysi\u0105ce monet - Instalki.pl", "description": "Cyfrowa nie\u015bmiertelno\u015b\u0107 ju\u017c dost\u0119pna. Wirtualny awatar za tysi\u0105ce monet - Instalki.pl", "link": "https://www.instalki.pl/aktualnosci/internet/59979-cyfrowa-niesmiertelnosc-projekt-koreanskiej-firmy.html", "date_published": "2023-07-21T08:57:59.494760+00:00", "persistent": false, "dead": false, "artist": null, "album": null, "user": null, "language": "pl-PL", "thumbnail": null}, {"source": "https://www.instalki.pl/aktualnosci", "title": "Jak wykorzysta\u0107 potencja\u0142 Internetu i odnie\u015b\u0107 sukces? Porady dla m\u0142odych inwestor\u00f3w - Instalki.pl", "description": "Jak wykorzysta\u0107 potencja\u0142 Internetu i odnie\u015b\u0107 sukces? Porady dla m\u0142odych inwestor\u00f3w - Instalki.pl", "link": "https://www.instalki.pl/aktualnosci/internet/59978-jak-wykorzystac-potencjal-internetu.html", "date_published": "2023-07-21T08:57:59.197363+00:00", "persistent": false, "dead": false, "artist": null, "album": null, "user": null, "language": "pl-PL", "thumbnail": null}, {"source": "https://www.instalki.pl/aktualnosci", "title": "Koniec z czekaniem na fizyczne prawo jazdy. mObywatel z rewolucyjn\u0105 nowo\u015bci\u0105 - Instalki.pl", "description": "Koniec z czekaniem na fizyczne prawo jazdy. mObywatel z rewolucyjn\u0105 nowo\u015bci\u0105 - Instalki.pl", "link": "https://www.instalki.pl/aktualnosci/software/59977-mobywatel-tymczasowe-prawo-jazdy.html", "date_published": "2023-07-21T07:52:52.613432+00:00", "persistent": false, "dead": false, "artist": null, "album": null, "user": null, "language": "pl-PL", "thumbnail": null}, {"source": "https://www.instalki.pl/aktualnosci", "title": "Netflix zablokowa\u0142 wsp\u00f3\u0142dzielenie kont na ca\u0142ym \u015bwiecie - Instalki.pl", "description": "Netflix zablokowa\u0142 wsp\u00f3\u0142dzielenie kont na ca\u0142ym \u015bwiecie - Instalki.pl", "link": "https://www.instalki.pl/aktualnosci/software/59976-netflix-wspoldzielenie-kont-zakaz-na-calym-swiecie.html", "date_published": "2023-07-21T06:48:09.994098+00:00", "persistent": false, "dead": false, "artist": null, "album": null, "user": null, "language": "pl-PL", "thumbnail": null}]