[{"source": "https://time.com/tech/feed", "title": "Ant Receives Chinese Government Nod to Roll Out AI Services", "description": "The fintech affiliate of Alibaba will roll out products powered by its large language model Bailing to the public.", "link": "https://time.com/6332071/ant-ai-services-bailing", "date_published": "2023-11-06T20:31:07+00:00", "permanent": false, "bookmarked": false, "dead": null, "artist": "TIME - tech", "album": "TIME - tech", "user": null, "language": "en-UK", "thumbnail": null, "age": null, "page_rating_contents": 0, "page_rating_votes": 0, "page_rating_visits": 0, "page_rating": 0, "tags": [], "comments": [], "vote": 0}]